CHANGELOG
LICENSE
MANIFEST.in
README.md
setup.py
rauth/__init__.py
rauth/compat.py
rauth/oauth.py
rauth/service.py
rauth/session.py
rauth/utils.py
rauth.egg-info/PKG-INFO
rauth.egg-info/SOURCES.txt
rauth.egg-info/dependency_links.txt
rauth.egg-info/not-zip-safe
rauth.egg-info/requires.txt
rauth.egg-info/top_level.txt